{
  "name": "Apply for legal aid",
  "description": "This service enables citizens and their solicitors to submit means and capital information, with supporting evidence, and solicitors to submit merit information.",
  "organisation": "Legal Aid Agency",
  "theme": "Crime, justice and the law",
  "phase": "beta",
  "liveservice": "https://apply-for-legal-aid.service.justice.gov.uk",
  "start-page": "https://www.gov.uk/guidance/apply-for-legal-aid",
  "tags": [
    "Top 75"
  ],
  "timeline": {
    "items": [
      {
        "label": "Passed alpha assessment",
        "date": "2018-06-25",
        "links": [
          {
            "href": "https://www.gov.uk/service-standard-reports/apply-for-legal-aid-alpha-assessment",
            "text": "service assessment report",
            "visuallyHiddenText": " for alpha assessment"
          }
        ]
      }
    ]
  },
  "sourceCode": [
    {
      "text": "Source code",
      "href": "https://github.com/ministryofjustice/laa-apply-for-legal-aid"
    }
  ]
}
